verify/fixtures/anomaly_test.v
`timescale 1ns/1ps

module anomaly_test;
    reg clk;
    reg rst_n;

    // Normal signal
    reg data_valid;

    // Stuck signal (will not change for a long time)
    reg stuck_signal;

    // Glitch signal (very short pulse)
    reg glitch_signal;

    // Metastability signal (will have x values)
    reg sync_flag;

    // Bus contention signal
    reg [7:0] data_bus;

    initial begin
        $dumpfile("anomaly_basic.vcd");
        $dumpvars(0, anomaly_test);

        clk = 0;
        rst_n = 0;
        data_valid = 0;
        stuck_signal = 0;
        glitch_signal = 0;
        sync_flag = 0;
        data_bus = 8'h00;

        // Reset
        #20 rst_n = 1;

        // Normal activity
        #20 data_valid = 1;
        #20 data_valid = 0;
        #20 data_valid = 1;
        #20 data_valid = 0;

        // Glitch: very short pulse (2ns)
        #20 glitch_signal = 1;
        #2  glitch_signal = 0;

        // Normal pulse for comparison (20ns)
        #20 glitch_signal = 1;
        #20 glitch_signal = 0;

        // Stuck signal starts here, will stay at 1 for a long time
        #20 stuck_signal = 1;

        // Metastability: x value
        #20 sync_flag = 1'bx;
        #10 sync_flag = 0;

        // More normal activity
        #20 data_valid = 1;
        #20 data_valid = 0;

        // Bus contention: all x values
        #20 data_bus = 8'hxx;
        #20 data_bus = 8'h00;

        // Another glitch
        #20 glitch_signal = 1;
        #1  glitch_signal = 0;

        // Continue with stuck_signal = 1 (totally stuck for >300ns)
        #500;

        // Finally, stuck_signal releases
        stuck_signal = 0;

        #50 $finish;
    end

    always #5 clk = ~clk;

endmodule

verify/fixtures/anomaly_basic.vcd
$date
	Tue May 26 23:09:53 2026
$end
$version
	Icarus Verilog
$end
$timescale
	1ps
$end
$scope module anomaly_test $end
$var reg 1 ! clk $end
$var reg 8 " data_bus [7:0] $end
$var reg 1 # data_valid $end
$var reg 1 $ glitch_signal $end
$var reg 1 % rst_n $end
$var reg 1 & stuck_signal $end
$var reg 1 ' sync_flag $end
$upscope $end
$enddefinitions $end
#0
$dumpvars
0'
0&
0%
0$
0#
b0 "
0!
$end
#5000
1!
#10000
0!
#15000
1!
#20000
0!
1%
#25000
1!
#30000
0!
#35000
1!
#40000
0!
1#
#45000
1!
#50000
0!
#55000
1!
#60000
0!
0#
#65000
1!
#70000
0!
#75000
1!
#80000
0!
1#
#85000
1!
#90000
0!
#95000
1!
#100000
0!
0#
#105000
1!
#110000
0!
#115000
1!
#120000
0!
1$
#122000
0$
#125000
1!
#130000
0!
#135000
1!
#140000
0!
#142000
1$
#145000
1!
#150000
0!
#155000
1!
#160000
0!
#162000
0$
#165000
1!
#170000
0!
#175000
1!
#180000
0!
#182000
1&
#185000
1!
#190000
0!
#195000
1!
#200000
0!
#202000
x'
#205000
1!
#210000
0!
#212000
0'
#215000
1!
#220000
0!
#225000
1!
#230000
0!
#232000
1#
#235000
1!
#240000
0!
#245000
1!
#250000
0!
#252000
0#
#255000
1!
#260000
0!
#265000
1!
#270000
0!
#272000
bx "
#275000
1!
#280000
0!
#285000
1!
#290000
0!
#292000
b0 "
#295000
1!
#300000
0!
#305000
1!
#310000
0!
#312000
1$
#313000
0$
