verify/fixtures/apb_test.v
`timescale 1ns/1ps

// APB3 protocol test
module apb_test;
    reg clk;
    reg rst_n;

    // APB signals
    reg [31:0] paddr;
    reg pwrite;
    reg psel;
    reg penable;
    reg [31:0] pwdata;
    reg pready;
    reg [31:0] prdata;
    reg pslverr;

    initial begin
        $dumpfile("apb_basic.vcd");
        $dumpvars(0, apb_test);

        clk = 0;
        rst_n = 0;
        paddr = 0;
        pwrite = 0;
        psel = 0;
        penable = 0;
        pwdata = 0;
        pready = 0;
        prdata = 0;
        pslverr = 0;

        #20 rst_n = 1;

        // APB Write Transaction 1: Write 0xDEADBEEF to 0x1000
        // SETUP phase
        #20 paddr = 32'h1000;
            pwrite = 1;
            pwdata = 32'hDEADBEEF;
            psel = 1;
        // ACCESS phase
        #10 penable = 1;
        // Slave ready
        #10 pready = 1;
        // Complete
        #10 psel = 0;
            penable = 0;
            pready = 0;

        // APB Read Transaction: Read from 0x1000
        #20 paddr = 32'h1000;
            pwrite = 0;
            psel = 1;
        #10 penable = 1;
        #10 pready = 1;
            prdata = 32'hDEADBEEF;
        #10 psel = 0;
            penable = 0;
            pready = 0;

        // APB Write with error
        #20 paddr = 32'h2000;
            pwrite = 1;
            pwdata = 32'hCAFEBABE;
            psel = 1;
        #10 penable = 1;
        #20 pready = 1;
            pslverr = 1;  // Slave error
        #10 psel = 0;
            penable = 0;
            pready = 0;
            pslverr = 0;

        #50 $finish;
    end

    always #5 clk = ~clk;

endmodule

verify/fixtures/apb_basic.vcd
$date
	Tue May 26 23:20:00 2026
$end
$version
	Icarus Verilog
$end
$timescale
	1ps
$end
$scope module apb_test $end
$var reg 1 ! clk $end
$var reg 32 " paddr [31:0] $end
$var reg 1 # penable $end
$var reg 32 $ prdata [31:0] $end
$var reg 1 % pready $end
$var reg 1 & psel $end
$var reg 1 ' pslverr $end
$var reg 32 ( pwdata [31:0] $end
$var reg 1 ) pwrite $end
$var reg 1 * rst_n $end
$upscope $end
$enddefinitions $end
#0
$dumpvars
0*
0)
b0 (
0'
0&
0%
b0 $
0#
b0 "
0!
$end
#5000
1!
#10000
0!
#15000
1!
#20000
0!
1*
#25000
1!
#30000
0!
#35000
1!
#40000
0!
1&
b11011110101011011011111011101111 (
1)
b1000000000000 "
#45000
1!
#50000
0!
1#
#55000
1!
#60000
0!
1%
#65000
1!
#70000
0!
0%
0#
0&
#75000
1!
#80000
0!
#85000
1!
#90000
0!
1&
0)
#95000
1!
#100000
0!
1#
#105000
1!
#110000
0!
b11011110101011011011111011101111 $
1%
#115000
1!
#120000
0!
0%
0#
0&
#125000
1!
#130000
0!
#135000
1!
#140000
0!
1&
b11001010111111101011101010111110 (
1)
b10000000000000 "
#145000
1!
#150000
0!
1#
#155000
1!
#160000
0!
#165000
1!
#170000
0!
1'
1%
#175000
1!
#180000
0!
0'
0%
0#
0&
