verify/fixtures/axi4_test.v
`timescale 1ns/1ps

module axi4_test;
    reg clk;
    reg rst_n;

    // AXI4 Write Address Channel
    reg m_axi_awvalid;
    reg m_axi_awready;
    reg [31:0] m_axi_awaddr;
    reg [7:0] m_axi_awlen;
    reg [2:0] m_axi_awsize;
    reg [1:0] m_axi_awburst;

    // AXI4 Write Data Channel
    reg m_axi_wvalid;
    reg m_axi_wready;
    reg [31:0] m_axi_wdata;
    reg [3:0] m_axi_wstrb;
    reg m_axi_wlast;

    // AXI4 Write Response Channel
    reg m_axi_bvalid;
    reg m_axi_bready;
    reg [1:0] m_axi_bresp;

    // AXI4 Read Address Channel
    reg m_axi_arvalid;
    reg m_axi_arready;
    reg [31:0] m_axi_araddr;
    reg [7:0] m_axi_arlen;

    // AXI4 Read Data Channel
    reg m_axi_rvalid;
    reg m_axi_rready;
    reg [31:0] m_axi_rdata;
    reg [1:0] m_axi_rresp;
    reg m_axi_rlast;

    initial begin
        $dumpfile("axi4_basic.vcd");
        $dumpvars(0, axi4_test);

        // Initialize
        clk = 0;
        rst_n = 0;
        m_axi_awvalid = 0;
        m_axi_awready = 0;
        m_axi_awaddr = 0;
        m_axi_awlen = 0;
        m_axi_awsize = 3'b010; // 4 bytes
        m_axi_awburst = 2'b01; // INCR
        m_axi_wvalid = 0;
        m_axi_wready = 0;
        m_axi_wdata = 0;
        m_axi_wstrb = 4'hF;
        m_axi_wlast = 0;
        m_axi_bvalid = 0;
        m_axi_bready = 0;
        m_axi_bresp = 2'b00; // OKAY
        m_axi_arvalid = 0;
        m_axi_arready = 0;
        m_axi_araddr = 0;
        m_axi_arlen = 0;
        m_axi_rvalid = 0;
        m_axi_rready = 0;
        m_axi_rdata = 0;
        m_axi_rresp = 2'b00;
        m_axi_rlast = 0;

        // Reset
        #20 rst_n = 1;

        // AXI Write Transaction 1: Single beat write to 0x1000
        #20;
        m_axi_awvalid = 1;
        m_axi_awaddr = 32'h1000;
        m_axi_awlen = 8'h00; // 1 beat

        #10 m_axi_awready = 1;
        #10 m_axi_awvalid = 0;
            m_axi_awready = 0;

        // Write data
        m_axi_wvalid = 1;
        m_axi_wdata = 32'hDEADBEEF;
        m_axi_wlast = 1;

        #10 m_axi_wready = 1;
        #10 m_axi_wvalid = 0;
            m_axi_wready = 0;
            m_axi_wlast = 0;

        // Write response
        m_axi_bvalid = 1;
        m_axi_bresp = 2'b00; // OKAY
        m_axi_bready = 1;

        #10 m_axi_bvalid = 0;
            m_axi_bready = 0;

        // AXI Write Transaction 2: Burst write (2 beats) to 0x2000
        #20;
        m_axi_awvalid = 1;
        m_axi_awaddr = 32'h2000;
        m_axi_awlen = 8'h01; // 2 beats

        #10 m_axi_awready = 1;
        #10 m_axi_awvalid = 0;
            m_axi_awready = 0;

        // Write data beat 1
        m_axi_wvalid = 1;
        m_axi_wdata = 32'hCAFEBABE;
        m_axi_wlast = 0;

        #10 m_axi_wready = 1;
        #10 m_axi_wdata = 32'h12345678;
            m_axi_wlast = 1;

        #10 m_axi_wvalid = 0;
            m_axi_wready = 0;
            m_axi_wlast = 0;

        // Write response
        m_axi_bvalid = 1;
        m_axi_bresp = 2'b00; // OKAY
        m_axi_bready = 1;

        #10 m_axi_bvalid = 0;
            m_axi_bready = 0;

        // AXI Read Transaction: Single beat read from 0x1000
        #20;
        m_axi_arvalid = 1;
        m_axi_araddr = 32'h1000;
        m_axi_arlen = 8'h00; // 1 beat

        #10 m_axi_arready = 1;
        #10 m_axi_arvalid = 0;
            m_axi_arready = 0;

        // Read data
        m_axi_rvalid = 1;
        m_axi_rdata = 32'hDEADBEEF;
        m_axi_rresp = 2'b00; // OKAY
        m_axi_rlast = 1;
        m_axi_rready = 1;

        #10 m_axi_rvalid = 0;
            m_axi_rready = 0;
            m_axi_rlast = 0;

        // Protocol Violation: WVALID before AWVALID
        #20;
        m_axi_wvalid = 1;
        m_axi_wdata = 32'hBADBAD00;

        #20 m_axi_wvalid = 0;

        #20;
        m_axi_awvalid = 1;
        m_axi_awaddr = 32'h3000;
        m_axi_awlen = 8'h00;

        #10 m_axi_awready = 1;
        #10 m_axi_awvalid = 0;
            m_axi_awready = 0;

        #50 $finish;
    end

    always #5 clk = ~clk;

endmodule

verify/fixtures/axi4_basic.vcd
$date
	Mon May 25 22:39:41 2026
$end
$version
	Icarus Verilog
$end
$timescale
	1ps
$end
$scope module axi4_test $end
$var reg 1 ! clk $end
$var reg 32 " m_axi_araddr [31:0] $end
$var reg 8 # m_axi_arlen [7:0] $end
$var reg 1 $ m_axi_arready $end
$var reg 1 % m_axi_arvalid $end
$var reg 32 & m_axi_awaddr [31:0] $end
$var reg 2 ' m_axi_awburst [1:0] $end
$var reg 8 ( m_axi_awlen [7:0] $end
$var reg 1 ) m_axi_awready $end
$var reg 3 * m_axi_awsize [2:0] $end
$var reg 1 + m_axi_awvalid $end
$var reg 1 , m_axi_bready $end
$var reg 2 - m_axi_bresp [1:0] $end
$var reg 1 . m_axi_bvalid $end
$var reg 32 / m_axi_rdata [31:0] $end
$var reg 1 0 m_axi_rlast $end
$var reg 1 1 m_axi_rready $end
$var reg 2 2 m_axi_rresp [1:0] $end
$var reg 1 3 m_axi_rvalid $end
$var reg 32 4 m_axi_wdata [31:0] $end
$var reg 1 5 m_axi_wlast $end
$var reg 1 6 m_axi_wready $end
$var reg 4 7 m_axi_wstrb [3:0] $end
$var reg 1 8 m_axi_wvalid $end
$var reg 1 9 rst_n $end
$upscope $end
$enddefinitions $end
#0
$dumpvars
09
08
b1111 7
06
05
b0 4
03
b0 2
01
00
b0 /
0.
b0 -
0,
0+
b10 *
0)
b0 (
b1 '
b0 &
0%
0$
b0 #
b0 "
0!
$end
#5000
1!
#10000
0!
#15000
1!
#20000
0!
19
#25000
1!
#30000
0!
#35000
1!
#40000
0!
b1000000000000 &
1+
#45000
1!
#50000
0!
1)
#55000
1!
#60000
0!
15
b11011110101011011011111011101111 4
18
0)
0+
#65000
1!
#70000
0!
16
#75000
1!
#80000
0!
1,
1.
05
06
08
#85000
1!
#90000
0!
0,
0.
#95000
1!
#100000
0!
#105000
1!
#110000
0!
b1 (
b10000000000000 &
1+
#115000
1!
#120000
0!
1)
#125000
1!
#130000
0!
b11001010111111101011101010111110 4
18
0)
0+
#135000
1!
#140000
0!
16
#145000
1!
#150000
0!
15
b10010001101000101011001111000 4
#155000
1!
#160000
0!
1,
1.
05
06
08
#165000
1!
#170000
0!
0,
0.
#175000
1!
#180000
0!
#185000
1!
#190000
0!
b1000000000000 "
1%
#195000
1!
#200000
0!
1$
#205000
1!
#210000
0!
11
10
b11011110101011011011111011101111 /
13
0$
0%
#215000
1!
#220000
0!
00
01
03
#225000
1!
#230000
0!
#235000
1!
#240000
0!
b10111010110110111010110100000000 4
18
#245000
1!
#250000
0!
#255000
1!
#260000
0!
08
#265000
1!
#270000
0!
#275000
1!
#280000
0!
b0 (
b11000000000000 &
1+
#285000
1!
#290000
0!
1)
#295000
1!
#300000
0!
0)
0+
