verify/fixtures/causality_test.v
`timescale 1ns/1ps

module causality_test;
    reg clk;
    reg rst_n;

    // Input signals (potential causes)
    reg input_valid;
    reg fifo_write;
    reg fifo_full;
    reg [7:0] timeout_counter;

    // Output signal (effect)
    reg error_flag;
    reg busy;

    // Unrelated signals
    reg unrelated_signal;
    reg [3:0] counter;

    initial begin
        $dumpfile("causality_basic.vcd");
        $dumpvars(0, causality_test);

        // Initialize
        clk = 0;
        rst_n = 0;
        input_valid = 0;
        fifo_write = 0;
        fifo_full = 0;
        timeout_counter = 0;
        error_flag = 0;
        busy = 0;
        unrelated_signal = 0;
        counter = 0;

        // Reset
        #20 rst_n = 1;

        // ============================================
        // Pattern 1: fifo_full -> error_flag (5 times)
        // This establishes a high correlation
        // ============================================
        #20 input_valid = 1;
            fifo_write = 1;
        #10 fifo_full = 1;
        #5  error_flag = 1;     // 5ns after fifo_full
        #10 error_flag = 0;
            fifo_full = 0;
            input_valid = 0;
            fifo_write = 0;

        #30 input_valid = 1;
            fifo_write = 1;
        #15 fifo_full = 1;
        #5  error_flag = 1;
        #10 error_flag = 0;
            fifo_full = 0;
            input_valid = 0;
            fifo_write = 0;

        #30 input_valid = 1;
            fifo_write = 1;
        #20 fifo_full = 1;
        #5  error_flag = 1;
        #10 error_flag = 0;
            fifo_full = 0;
            input_valid = 0;
            fifo_write = 0;

        #30 input_valid = 1;
            fifo_write = 1;
        #10 fifo_full = 1;
        #5  error_flag = 1;
        #10 error_flag = 0;
            fifo_full = 0;
            input_valid = 0;
            fifo_write = 0;

        // ============================================
        // Some unrelated activity (noise)
        // ============================================
        #30 unrelated_signal = 1;
        #20 counter = 1;
        #20 counter = 2;
        #20 unrelated_signal = 0;
        #20 counter = 3;

        // ============================================
        // Pattern 2: The "target" event we want to analyze
        // At T=500ns, error_flag goes high
        // Just before, fifo_full and timeout_counter changed
        // ============================================
        #20 busy = 1;                  // T=470ns
        #10 timeout_counter = 100;     // T=480ns
        #10 fifo_full = 1;             // T=490ns
        #10 error_flag = 1;            // T=500ns (THE EFFECT WE INVESTIGATE)
        #20 error_flag = 0;
            fifo_full = 0;
            busy = 0;
            timeout_counter = 0;

        #50 $finish;
    end

    always #5 clk = ~clk;

endmodule

verify/fixtures/causality_basic.vcd
$date
	Tue May 26 22:55:56 2026
$end
$version
	Icarus Verilog
$end
$timescale
	1ps
$end
$scope module causality_test $end
$var reg 1 ! busy $end
$var reg 1 " clk $end
$var reg 4 # counter [3:0] $end
$var reg 1 $ error_flag $end
$var reg 1 % fifo_full $end
$var reg 1 & fifo_write $end
$var reg 1 ' input_valid $end
$var reg 1 ( rst_n $end
$var reg 8 ) timeout_counter [7:0] $end
$var reg 1 * unrelated_signal $end
$upscope $end
$enddefinitions $end
#0
$dumpvars
0*
b0 )
0(
0'
0&
0%
0$
b0 #
0"
0!
$end
#5000
1"
#10000
0"
#15000
1"
#20000
0"
1(
#25000
1"
#30000
0"
#35000
1"
#40000
0"
1&
1'
#45000
1"
#50000
0"
1%
#55000
1"
1$
#60000
0"
#65000
1"
0&
0'
0%
0$
#70000
0"
#75000
1"
#80000
0"
#85000
1"
#90000
0"
#95000
1"
1&
1'
#100000
0"
#105000
1"
#110000
0"
1%
#115000
1"
1$
#120000
0"
#125000
1"
0&
0'
0%
0$
#130000
0"
#135000
1"
#140000
0"
#145000
1"
#150000
0"
#155000
1"
1&
1'
#160000
0"
#165000
1"
#170000
0"
#175000
1"
1%
#180000
0"
1$
#185000
1"
#190000
0"
0&
0'
0%
0$
#195000
1"
#200000
0"
#205000
1"
#210000
0"
#215000
1"
#220000
0"
1&
1'
#225000
1"
#230000
0"
1%
#235000
1"
1$
#240000
0"
#245000
1"
0&
0'
0%
0$
#250000
0"
#255000
1"
#260000
0"
#265000
1"
#270000
0"
#275000
1"
1*
#280000
0"
#285000
1"
#290000
0"
#295000
1"
b1 #
#300000
0"
#305000
1"
#310000
0"
#315000
1"
b10 #
#320000
0"
#325000
1"
#330000
0"
#335000
1"
0*
#340000
0"
#345000
1"
#350000
0"
#355000
1"
b11 #
#360000
0"
#365000
1"
#370000
0"
#375000
1"
1!
#380000
0"
#385000
1"
b1100100 )
#390000
0"
#395000
1"
1%
#400000
0"
#405000
1"
1$
#410000
0"
#415000
1"
#420000
0"
#425000
1"
b0 )
0!
0%
0$
