verify/fixtures/fsm_test.v
`timescale 1ns/1ps

module fsm_test;
    reg clk;
    reg rst_n;
    reg start;
    reg done;
    reg error;
    reg [2:0] state;
    reg [2:0] next_state;

    // State encoding
    localparam IDLE  = 3'b000;
    localparam START = 3'b001;
    localparam BUSY  = 3'b010;
    localparam WAIT  = 3'b011;
    localparam DONE  = 3'b100;
    localparam ERROR = 3'b111;

    initial begin
        $dumpfile("fsm_basic.vcd");
        $dumpvars(0, fsm_test);

        // Initialize
        clk = 0;
        rst_n = 0;
        start = 0;
        done = 0;
        error = 0;
        state = IDLE;

        // Reset
        #20 rst_n = 1;

        // Normal flow: IDLE -> START -> BUSY -> DONE -> IDLE
        #20 start = 1;
        #10 state = START;
        #10 start = 0;
        #10 state = BUSY;
        #50 state = DONE;
        #10 done = 1;
        #10 state = IDLE;
            done = 0;

        // Flow with wait: IDLE -> START -> BUSY -> WAIT -> BUSY -> DONE -> IDLE
        #20 start = 1;
        #10 state = START;
        #10 start = 0;
        #10 state = BUSY;
        #30 state = WAIT;
        #100 state = BUSY;  // Stuck in WAIT for 100ns
        #20 state = DONE;
        #10 done = 1;
        #10 state = IDLE;
            done = 0;

        // Error flow: IDLE -> START -> BUSY -> ERROR -> IDLE
        #20 start = 1;
        #10 state = START;
        #10 start = 0;
        #10 state = BUSY;
        #30 error = 1;
        #10 state = ERROR;
        #20 error = 0;
        #10 state = IDLE;

        // Stuck in BUSY (anomaly)
        #20 start = 1;
        #10 state = START;
        #10 start = 0;
        #10 state = BUSY;
        #200;  // Stuck for 200ns

        #50 $finish;
    end

    always #5 clk = ~clk;

endmodule

verify/fixtures/fsm_basic.vcd
$date
	Mon May 25 22:49:48 2026
$end
$version
	Icarus Verilog
$end
$timescale
	1ps
$end
$scope module fsm_test $end
$var reg 1 ! clk $end
$var reg 1 " done $end
$var reg 1 # error $end
$var reg 1 $ rst_n $end
$var reg 1 % start $end
$var reg 3 & state [2:0] $end
$upscope $end
$enddefinitions $end
#0
$dumpvars
b0 &
0%
0$
0#
0"
0!
$end
#5000
1!
#10000
0!
#15000
1!
#20000
0!
1$
#25000
1!
#30000
0!
#35000
1!
#40000
0!
1%
#45000
1!
#50000
0!
b1 &
#55000
1!
#60000
0!
0%
#65000
1!
#70000
0!
b10 &
#75000
1!
#80000
0!
#85000
1!
#90000
0!
#95000
1!
#100000
0!
#105000
1!
#110000
0!
#115000
1!
#120000
0!
b100 &
#125000
1!
#130000
0!
1"
#135000
1!
#140000
0!
0"
b0 &
#145000
1!
#150000
0!
#155000
1!
#160000
0!
1%
#165000
1!
#170000
0!
b1 &
#175000
1!
#180000
0!
0%
#185000
1!
#190000
0!
b10 &
#195000
1!
#200000
0!
#205000
1!
#210000
0!
#215000
1!
#220000
0!
b11 &
#225000
1!
#230000
0!
#235000
1!
#240000
0!
#245000
1!
#250000
0!
#255000
1!
#260000
0!
#265000
1!
#270000
0!
#275000
1!
#280000
0!
#285000
1!
#290000
0!
#295000
1!
#300000
0!
#305000
1!
#310000
0!
#315000
1!
#320000
0!
b10 &
#325000
1!
#330000
0!
#335000
1!
#340000
0!
b100 &
#345000
1!
#350000
0!
1"
#355000
1!
#360000
0!
0"
b0 &
#365000
1!
#370000
0!
#375000
1!
#380000
0!
1%
#385000
1!
#390000
0!
b1 &
#395000
1!
#400000
0!
0%
#405000
1!
#410000
0!
b10 &
#415000
1!
#420000
0!
#425000
1!
#430000
0!
#435000
1!
#440000
0!
1#
#445000
1!
#450000
0!
b111 &
#455000
1!
#460000
0!
#465000
1!
#470000
0!
0#
#475000
1!
#480000
0!
b0 &
#485000
1!
#490000
0!
#495000
1!
#500000
0!
1%
#505000
1!
#510000
0!
b1 &
#515000
1!
#520000
0!
0%
#525000
1!
#530000
0!
b10 &
