verify/fixtures/uart_test.v
`timescale 1ns/1ps

// UART protocol test (115200 baud, 1 start, 8 data, 1 stop, no parity)
// Bit time at 115200 baud = ~8.68us, but we use simplified timing for testing
module uart_test;
    reg clk;
    reg rst_n;
    reg uart_tx;
    reg uart_rx;

    // Simplified UART: 1 bit = 100ns
    parameter BIT_TIME = 100;

    task send_byte(input [7:0] data);
        integer i;
        begin
            // Start bit (0)
            uart_tx = 0;
            #BIT_TIME;

            // Data bits (LSB first)
            for (i = 0; i < 8; i = i + 1) begin
                uart_tx = data[i];
                #BIT_TIME;
            end

            // Stop bit (1)
            uart_tx = 1;
            #BIT_TIME;
        end
    endtask

    initial begin
        $dumpfile("uart_basic.vcd");
        $dumpvars(0, uart_test);

        clk = 0;
        rst_n = 0;
        uart_tx = 1;  // Idle is high
        uart_rx = 1;

        #20 rst_n = 1;

        // Idle for a bit
        #100;

        // Send 'A' (0x41) on TX
        send_byte(8'h41);

        // Brief gap
        #100;

        // Send 'B' (0x42) on TX
        send_byte(8'h42);

        // Brief gap
        #200;

        // Send 'C' (0x43)
        send_byte(8'h43);

        #100 $finish;
    end

    always #5 clk = ~clk;

endmodule

verify/fixtures/uart_basic.vcd
$date
	Tue May 26 23:20:00 2026
$end
$version
	Icarus Verilog
$end
$timescale
	1ps
$end
$scope module uart_test $end
$var reg 1 ! clk $end
$var reg 1 " rst_n $end
$var reg 1 # uart_rx $end
$var reg 1 $ uart_tx $end
$scope task send_byte $end
$var reg 8 % data [7:0] $end
$var integer 32 & i [31:0] $end
$upscope $end
$upscope $end
$enddefinitions $end
#0
$dumpvars
bx &
bx %
1$
1#
0"
0!
$end
#5000
1!
#10000
0!
#15000
1!
#20000
0!
1"
#25000
1!
#30000
0!
#35000
1!
#40000
0!
#45000
1!
#50000
0!
#55000
1!
#60000
0!
#65000
1!
#70000
0!
#75000
1!
#80000
0!
#85000
1!
#90000
0!
#95000
1!
#100000
0!
#105000
1!
#110000
0!
#115000
1!
#120000
0!
0$
b1000001 %
#125000
1!
#130000
0!
#135000
1!
#140000
0!
#145000
1!
#150000
0!
#155000
1!
#160000
0!
#165000
1!
#170000
0!
#175000
1!
#180000
0!
#185000
1!
#190000
0!
#195000
1!
#200000
0!
#205000
1!
#210000
0!
#215000
1!
#220000
0!
1$
b0 &
#225000
1!
#230000
0!
#235000
1!
#240000
0!
#245000
1!
#250000
0!
#255000
1!
#260000
0!
#265000
1!
#270000
0!
#275000
1!
#280000
0!
#285000
1!
#290000
0!
#295000
1!
#300000
0!
#305000
1!
#310000
0!
#315000
1!
#320000
0!
0$
b1 &
#325000
1!
#330000
0!
#335000
1!
#340000
0!
#345000
1!
#350000
0!
#355000
1!
#360000
0!
#365000
1!
#370000
0!
#375000
1!
#380000
0!
#385000
1!
#390000
0!
#395000
1!
#400000
0!
#405000
1!
#410000
0!
#415000
1!
#420000
0!
b10 &
#425000
1!
#430000
0!
#435000
1!
#440000
0!
#445000
1!
#450000
0!
#455000
1!
#460000
0!
#465000
1!
#470000
0!
#475000
1!
#480000
0!
#485000
1!
#490000
0!
#495000
1!
#500000
0!
#505000
1!
#510000
0!
#515000
1!
#520000
0!
b11 &
#525000
1!
#530000
0!
#535000
1!
#540000
0!
#545000
1!
#550000
0!
#555000
1!
#560000
0!
#565000
1!
#570000
0!
#575000
1!
#580000
0!
#585000
1!
#590000
0!
#595000
1!
#600000
0!
#605000
1!
#610000
0!
#615000
1!
#620000
0!
b100 &
#625000
1!
#630000
0!
#635000
1!
#640000
0!
#645000
1!
#650000
0!
#655000
1!
#660000
0!
#665000
1!
#670000
0!
#675000
1!
#680000
0!
#685000
1!
#690000
0!
#695000
1!
#700000
0!
#705000
1!
#710000
0!
#715000
1!
#720000
0!
b101 &
#725000
1!
#730000
0!
#735000
1!
#740000
0!
#745000
1!
#750000
0!
#755000
1!
#760000
0!
#765000
1!
#770000
0!
#775000
1!
#780000
0!
#785000
1!
#790000
0!
#795000
1!
#800000
0!
#805000
1!
#810000
0!
#815000
1!
#820000
0!
1$
b110 &
#825000
1!
#830000
0!
#835000
1!
#840000
0!
#845000
1!
#850000
0!
#855000
1!
#860000
0!
#865000
1!
#870000
0!
#875000
1!
#880000
0!
#885000
1!
#890000
0!
#895000
1!
#900000
0!
#905000
1!
#910000
0!
#915000
1!
#920000
0!
0$
b111 &
#925000
1!
#930000
0!
#935000
1!
#940000
0!
#945000
1!
#950000
0!
#955000
1!
#960000
0!
#965000
1!
#970000
0!
#975000
1!
#980000
0!
#985000
1!
#990000
0!
#995000
1!
#1000000
0!
#1005000
1!
#1010000
0!
#1015000
1!
#1020000
0!
1$
b1000 &
#1025000
1!
#1030000
0!
#1035000
1!
#1040000
0!
#1045000
1!
#1050000
0!
#1055000
1!
#1060000
0!
#1065000
1!
#1070000
0!
#1075000
1!
#1080000
0!
#1085000
1!
#1090000
0!
#1095000
1!
#1100000
0!
#1105000
1!
#1110000
0!
#1115000
1!
#1120000
0!
#1125000
1!
#1130000
0!
#1135000
1!
#1140000
0!
#1145000
1!
#1150000
0!
#1155000
1!
#1160000
0!
#1165000
1!
#1170000
0!
#1175000
1!
#1180000
0!
#1185000
1!
#1190000
0!
#1195000
1!
#1200000
0!
#1205000
1!
#1210000
0!
#1215000
1!
#1220000
0!
0$
b1000010 %
#1225000
1!
#1230000
0!
#1235000
1!
#1240000
0!
#1245000
1!
#1250000
0!
#1255000
1!
#1260000
0!
#1265000
1!
#1270000
0!
#1275000
1!
#1280000
0!
#1285000
1!
#1290000
0!
#1295000
1!
#1300000
0!
#1305000
1!
#1310000
0!
#1315000
1!
#1320000
0!
b0 &
#1325000
1!
#1330000
0!
#1335000
1!
#1340000
0!
#1345000
1!
#1350000
0!
#1355000
1!
#1360000
0!
#1365000
1!
#1370000
0!
#1375000
1!
#1380000
0!
#1385000
1!
#1390000
0!
#1395000
1!
#1400000
0!
#1405000
1!
#1410000
0!
#1415000
1!
#1420000
0!
1$
b1 &
#1425000
1!
#1430000
0!
#1435000
1!
#1440000
0!
#1445000
1!
#1450000
0!
#1455000
1!
#1460000
0!
#1465000
1!
#1470000
0!
#1475000
1!
#1480000
0!
#1485000
1!
#1490000
0!
#1495000
1!
#1500000
0!
#1505000
1!
#1510000
0!
#1515000
1!
#1520000
0!
0$
b10 &
#1525000
1!
#1530000
0!
#1535000
1!
#1540000
0!
#1545000
1!
#1550000
0!
#1555000
1!
#1560000
0!
#1565000
1!
#1570000
0!
#1575000
1!
#1580000
0!
#1585000
1!
#1590000
0!
#1595000
1!
#1600000
0!
#1605000
1!
#1610000
0!
#1615000
1!
#1620000
0!
b11 &
#1625000
1!
#1630000
0!
#1635000
1!
#1640000
0!
#1645000
1!
#1650000
0!
#1655000
1!
#1660000
0!
#1665000
1!
#1670000
0!
#1675000
1!
#1680000
0!
#1685000
1!
#1690000
0!
#1695000
1!
#1700000
0!
#1705000
1!
#1710000
0!
#1715000
1!
#1720000
0!
b100 &
#1725000
1!
#1730000
0!
#1735000
1!
#1740000
0!
#1745000
1!
#1750000
0!
#1755000
1!
#1760000
0!
#1765000
1!
#1770000
0!
#1775000
1!
#1780000
0!
#1785000
1!
#1790000
0!
#1795000
1!
#1800000
0!
#1805000
1!
#1810000
0!
#1815000
1!
#1820000
0!
b101 &
#1825000
1!
#1830000
0!
#1835000
1!
#1840000
0!
#1845000
1!
#1850000
0!
#1855000
1!
#1860000
0!
#1865000
1!
#1870000
0!
#1875000
1!
#1880000
0!
#1885000
1!
#1890000
0!
#1895000
1!
#1900000
0!
#1905000
1!
#1910000
0!
#1915000
1!
#1920000
0!
1$
b110 &
#1925000
1!
#1930000
0!
#1935000
1!
#1940000
0!
#1945000
1!
#1950000
0!
#1955000
1!
#1960000
0!
#1965000
1!
#1970000
0!
#1975000
1!
#1980000
0!
#1985000
1!
#1990000
0!
#1995000
1!
#2000000
0!
#2005000
1!
#2010000
0!
#2015000
1!
#2020000
0!
0$
b111 &
#2025000
1!
#2030000
0!
#2035000
1!
#2040000
0!
#2045000
1!
#2050000
0!
#2055000
1!
#2060000
0!
#2065000
1!
#2070000
0!
#2075000
1!
#2080000
0!
#2085000
1!
#2090000
0!
#2095000
1!
#2100000
0!
#2105000
1!
#2110000
0!
#2115000
1!
#2120000
0!
1$
b1000 &
